dictgest/__init__.py
dictgest/cast.py
dictgest/converter.py
dictgest/routes.py
dictgest/serdes.py
dictgest/utils.py
dictgest-0.4.0.dist-info/LICENSE.txt
dictgest-0.4.0.dist-info/METADATA
dictgest-0.4.0.dist-info/WHEEL
dictgest-0.4.0.dist-info/top_level.txt
dictgest-0.4.0.dist-info/RECORD
