Metadata-Version: 2.1
Name: dictgest
Version: 0.4.0
Summary: Advanced dictionary ingestion into python objects
Home-page: https://github.com/bmsan/DictGest
Author: Bogdan Sandoi
Author-email: bogdan.sandoi@gmail.com
Classifier: Programming Language :: Python :: 3
Classifier: License :: OSI Approved :: MIT License
Classifier: Operating System :: OS Independent
Requires-Python: >=3.9
License-File: LICENSE.txt
Requires-Dist: python-dateutil (>=2.8.2)
Requires-Dist: setuptools (>=45.2.0)
